synacell/__init__.py
synacell/signal.py
synacell/cmodule/__init__.py
synacell/cmodule/snn.py
synacell/cmodule/lib/snn.dll
synacell/data/audio/down/00176480_nohash_0.wav
synacell/data/audio/down/004ae714_nohash_0.wav
synacell/data/audio/down/00b01445_nohash_0.wav
synacell/data/audio/down/00b01445_nohash_1.wav
synacell/data/audio/down/030ec18b_nohash_1.wav
synacell/data/audio/down/03cf93b1_nohash_1.wav
synacell/data/audio/happy/012c8314_nohash_0.wav
synacell/data/audio/happy/0135f3f2_nohash_0.wav
synacell/data/audio/happy/014f9f65_nohash_0.wav
synacell/data/audio/happy/0227998e_nohash_1.wav
synacell/data/audio/happy/05739450_nohash_1.wav
synacell/data/audio/happy/060cd039_nohash_1.wav
synacell/examples/SynaRCA-itAdjust.asc
synacell/examples/SynaRCA-itAdjust.raw
synacell/examples/SynaRCA-ode1.asc
synacell/examples/SynaRCA-ode1.raw
synacell/examples/SynaRCA-ode2.asc
synacell/examples/SynaRCA-ode2.raw
synacell/examples/SynaRCA-smallCp.asc
synacell/examples/SynaRCA-smallCp.raw
synacell/examples/__init__.py
synacell/examples/example_dft.py
synacell/examples/example_part.py
synacell/examples/example_plot_train.py
synacell/examples/example_spice.py
synacell/examples/example_train_dft.py
synacell/test/__init__.py
synacell/test/test_plot.py
synacell/test/test_simple.py
synacell/test/testfunc.py
synacell-0.0.11.dist-info/LICENSE
synacell-0.0.11.dist-info/METADATA
synacell-0.0.11.dist-info/WHEEL
synacell-0.0.11.dist-info/top_level.txt
synacell-0.0.11.dist-info/RECORD
