Metadata-Version: 2.1
Name: synacell
Version: 0.0.11
Summary: Synapses and cells
Home-page: https://github.com/GinkoBalboa/synacell
Author: Ginko Balboa
Author-email: ginkobalboa3@gmail.com
License: UNKNOWN
Platform: Windows 10 x64
Classifier: Development Status :: 1 - Planning
Classifier: Intended Audience :: Science/Research
Classifier: Intended Audience :: Developers
Classifier: Intended Audience :: Education
Classifier: License :: OSI Approved :: GNU Lesser General Public License v3 (LGPLv3)
Classifier: Programming Language :: Python :: 3.7
Classifier: Programming Language :: C++
Classifier: Natural Language :: English
Classifier: Operating System :: Microsoft :: Windows :: Windows 10
Classifier: Topic :: Scientific/Engineering :: Physics
Classifier: Topic :: Scientific/Engineering :: Artificial Intelligence
Requires-Python: >=3.7
Provides-Extra: data
Requires-Dist: pandas (>=1.0.0) ; extra == 'data'
Requires-Dist: numpy (>=1.18.0) ; extra == 'data'
Provides-Extra: plotting
Requires-Dist: matplotlib (>=2.2.0) ; extra == 'plotting'
Provides-Extra: spice
Requires-Dist: ltspice (>=0.4.2) ; extra == 'spice'
